idiosync/__init__.py
idiosync/__main__.py
idiosync/base.py
idiosync/cli.py
idiosync/config.py
idiosync/dummy.py
idiosync/freeipa.py
idiosync/ldap.py
idiosync/mediawiki.py
idiosync/requesttracker.py
idiosync/rfc2307.py
idiosync/sqlalchemy.py
idiosync/sync.py
idiosync/syncrepl.py
idiosync-0.0.1.dist-info/METADATA
idiosync-0.0.1.dist-info/WHEEL
idiosync-0.0.1.dist-info/entry_points.txt
idiosync-0.0.1.dist-info/top_level.txt
idiosync-0.0.1.dist-info/RECORD
