Metadata-Version: 2.1
Name: idiosync
Version: 0.0.1
Summary: Synchronize user databases
Home-page: https://github.com/unipartdigital/idiosync
Author: Michael Brown
Author-email: mbrown@fensystems.co.uk
License: GPLv2+
Platform: UNKNOWN
Classifier: Development Status :: 3 - Alpha
Classifier: Environment :: Console
Classifier: Intended Audience :: System Administrators
Classifier: License :: OSI Approved :: GNU General Public License v2 or later (GPLv2+)
Classifier: Programming Language :: Python :: 3
Classifier: Topic :: Security
Classifier: Topic :: System :: Systems Administration :: Authentication/Directory
Requires-Dist: alembic
Requires-Dist: pyasn1
Requires-Dist: python-ldap
Requires-Dist: pyyaml
Requires-Dist: sqlalchemy
